ptplot/__init__.py
ptplot/_version.py
ptplot/animation.py
ptplot/callback.py
ptplot/core.py
ptplot/facet.py
ptplot/hover.py
ptplot/nfl.py
ptplot/pick.py
ptplot/pick.ts
ptplot/plot.py
ptplot/ptplot.py
ptplot/utils.py
ptplot-0.3.1.dist-info/AUTHORS.rst
ptplot-0.3.1.dist-info/LICENSE
ptplot-0.3.1.dist-info/METADATA
ptplot-0.3.1.dist-info/WHEEL
ptplot-0.3.1.dist-info/top_level.txt
ptplot-0.3.1.dist-info/RECORD
