Metadata-Version: 2.1
Name: ptplot
Version: 0.3.1
Summary: Make beautiful plots of player tracking data
Home-page: https://github.com/AndrewRook/ptplot
Author: Andrew Schechtman-Rook
Author-email: footballastronomer@gmail.com
License: GNU General Public License v3
Keywords: ptplot
Platform: UNKNOWN
Classifier: Development Status :: 3 - Alpha
Classifier: Intended Audience :: Developers
Classifier: License :: OSI Approved :: GNU General Public License v3 (GPLv3)
Classifier: Natural Language :: English
Classifier: Programming Language :: Python :: 3
Classifier: Programming Language :: Python :: 3.7
Classifier: Programming Language :: Python :: 3.8
Classifier: Programming Language :: Python :: 3.9
Requires-Python: >=3.7
Requires-Dist: bokeh (>=2.3.3)
Requires-Dist: numpy (>=1.19.5)
Requires-Dist: pandas (>=1.2.0)
Requires-Dist: patsy (>=0.5.1)
Requires-Dist: pip (>=20.3.3)
Requires-Dist: svgpathtools (>=1.4.1)
Provides-Extra: dev
Requires-Dist: black (>=20.8b1) ; extra == 'dev'
Requires-Dist: flake8 (>=3.8.4) ; extra == 'dev'
Requires-Dist: mypy (>=0.910) ; extra == 'dev'
Requires-Dist: notebook (>=6.2.0) ; extra == 'dev'
Requires-Dist: pytest (>=6.2.1) ; extra == 'dev'
Requires-Dist: pytest-cov (>=2.11.1) ; extra == 'dev'
Requires-Dist: tox (>=3.21.4) ; extra == 'dev'
